syn_fifo.v
module syn_fifo(clk,rst,we,re,data,read_data);

parameter pointer_size='d3,depth='d8,width='d4;

reg [pointer_size-1:0] wp,rp; 
input clk,rst,we,re;
reg[width-1:0] fifo[depth-1:0];
input[width-1:0] data;
integer i;
output reg [width-1:0] read_data;

always @(posedge clk)
begin
    
    if(rst) 
    begin
        for(i=0;i<=depth-1;i=i+1)
        fifo[i]='d0;
        wp='d0;
        rp='d0;
    end
    else if(we)
    begin
        if(wp==depth-1 && rp=='d0)
        begin
            fifo[wp]=data;
            wp=0; 
            $display("fifo is full");
        end
        else
        begin
            fifo[wp]=data;
            wp=wp+1;
        end
    end
    else if(re)
    begin
        if(rp==depth-1)
        begin
            $display("fifo is empty");
            read_data=fifo[rp];
            fifo[rp]='d0;
            rp=0;
        end
        else
        begin
            read_data=fifo[rp];
            fifo[rp]='d0; 
            rp=rp+1;
        end
    end
    else
    begin
        wp=wp;
        rp=rp;
        $display("No Operation");
    end
end

endmodule

syn_fifo_test.v
`include "syn_fifo.v"
module syn_fifo_test;

//Inputs
reg clk,rst,we,re;
reg [3:0] data;

//Outputs
wire [3:0] read_data;
//Instatntiate the Unit Under Test(UUT)
syn_fifo uut(
    .clk(clk),
    .rst(rst),
    .we(we),
    .re(re),
    .data(data),
    .read_data(read_data)
);
always #30 clk=~clk;

initial begin
    $dumpfile("syn_fifo_test.vcd");
    $dumpvars(0,syn_fifo_test);
    //Initialize Inputs
    clk=1;rst=1;we=0;re=0;data=0;
    //Wait for 100ns for global reset to finish
    #60;we=1;data='d7;rst=0;
    //#20;we=0;re=1;rst=0;
    
    //Add stimulus here
    #60;we=1;data='d1;re=0;
    #60;we=1;data='d2;
    #60;we=1;data='d3;
    #60;we=1;data='d6;
    #60;we=1;data='d5;
    #60;we=1;data='d4;
    #60;we=1;data='d7;

    #60;re=1;we=0;
    #60;
    $finish;
end
endmodule

syn_fifo_test.vcd
$date
	Fri Jul 22 16:50:31 2022
$end
$version
	Icarus Verilog
$end
$timescale
	1s
$end
$scope module syn_fifo_test $end
$var wire 4 ! read_data [3:0] $end
$var reg 1 " clk $end
$var reg 4 # data [3:0] $end
$var reg 1 $ re $end
$var reg 1 % rst $end
$var reg 1 & we $end
$scope module uut $end
$var wire 1 ' clk $end
$var wire 4 ( data [3:0] $end
$var wire 1 ) re $end
$var wire 1 * rst $end
$var wire 1 + we $end
$var integer 32 , i [31:0] $end
$var reg 4 - read_data [3:0] $end
$var reg 3 . rp [2:0] $end
$var reg 3 / wp [2:0] $end
$upscope $end
$upscope $end
$enddefinitions $end
#0
$dumpvars
b0 /
b0 .
bx -
b1000 ,
0+
1*
0)
b0 (
1'
0&
1%
0$
b0 #
1"
bx !
$end
#30
0"
0'
#60
b1 /
1"
1'
0%
0*
b111 #
b111 (
1&
1+
#90
0"
0'
#120
b10 /
1"
1'
b1 #
b1 (
#150
0"
0'
#180
b11 /
1"
1'
b10 #
b10 (
#210
0"
0'
#240
b100 /
1"
1'
b11 #
b11 (
#270
0"
0'
#300
b101 /
1"
1'
b110 #
b110 (
#330
0"
0'
#360
b110 /
1"
1'
b101 #
b101 (
#390
0"
0'
#420
b111 /
1"
1'
b100 #
b100 (
#450
0"
0'
#480
b0 /
1"
1'
b111 #
b111 (
#510
0"
0'
#540
b1 .
b111 -
b111 !
1"
1'
0&
0+
1$
1)
#570
0"
0'
#600
b10 .
b1 -
b1 !
1"
1'
